veolia_api/__init__.py
veolia_api/constants.py
veolia_api/exceptions.py
veolia_api/model.py
veolia_api/veolia_api.py
veolia_api-2.1.0.dist-info/METADATA
veolia_api-2.1.0.dist-info/WHEEL
veolia_api-2.1.0.dist-info/licenses/LICENSE
veolia_api-2.1.0.dist-info/RECORD
