Metadata-Version: 2.4
Name: veolia_api
Version: 2.1.0
Summary: Client API for eau.veolia.fr
License: MIT
License-File: LICENSE
Keywords: python,veolia
Author: Jezza34000
Author-email: info@mail.com
Requires-Python: >=3.11
Classifier: License :: OSI Approved :: MIT License
Classifier: Operating System :: OS Independent
Classifier: Programming Language :: Python :: 3
Classifier: Programming Language :: Python :: 3.11
Classifier: Programming Language :: Python :: 3.12
Classifier: Programming Language :: Python :: 3.13
Classifier: Programming Language :: Python :: 3.14
Requires-Dist: aiohttp (>=3.11.11,<4.0.0)
Requires-Dist: tenacity (>=9.1.2,<10.0.0)
Project-URL: Homepage, https://github.com/Jezza34000/veolia-api
Project-URL: Repository, https://github.com/Jezza34000/veolia-api
